[
  {
    "id": 1,
    "title": "IA médica supera especialistas em diagnósticos",
    "summary": "Nova IA acerta mais que humanos em exames clínicos. Início de uma nova era na medicina.",
    "date": "2025-05-30"
  },
  {
    "id": 2,
    "title": "6G promete internet 100x mais rápida",
    "summary": "Primeiros testes mostram velocidades nunca vistas antes em redes móveis.",
    "date": "2025-05-29"
  },
  {
    "id": 3,
    "title": "Startups verdes atraem bilhões em 2025",
    "summary": "Soluções ecológicas estão ganhando o mercado com força.",
    "date": "2025-05-28"
  },
  {
    "id": 4,
    "title": "Realidade mista revoluciona o ensino",
    "summary": "Salas de aula imersivas são testadas em universidades brasileiras.",
    "date": "2025-05-27"
  },
  {
    "id": 5,
    "title": "Fusão nuclear mais próxima de se tornar viável",
    "summary": "Pesquisadores atingem novo marco de eficiência energética.",
    "date": "2025-05-26"
  },
  {
    "id": 6,
    "title": "IA médica supera especialistas em diagnósticos",
    "summary": "Nova IA acerta mais que humanos em exames clínicos. Início de uma nova era na medicina.",
    "date": "2025-05-30"
  },
  {
    "id": 7,
    "title": "6G promete internet 100x mais rápida",
    "summary": "Primeiros testes mostram velocidades nunca vistas antes em redes móveis.",
    "date": "2025-05-29"
  },
  {
    "id": 7,
    "title": "Startups verdes atraem bilhões em 2025",
    "summary": "Soluções ecológicas estão ganhando o mercado com força.",
    "date": "2025-05-28"
  },
  {
    "id": 8,
    "title": "Realidade mista revoluciona o ensino",
    "summary": "Salas de aula imersivas são testadas em universidades brasileiras.",
    "date": "2025-05-27"
  },
  {
    "id": 9,
    "title": "Fusão nuclear mais próxima de se tornar viável",
    "summary": "Pesquisadores atingem novo marco de eficiência energética.",
    "date": "2025-05-26"
  },
  {
    "id": 10,
    "title": "Fusão nuclear mais próxima de se tornar viável",
    "summary": "Pesquisadores atingem novo marco de eficiência energética.",
    "date": "2025-05-26"
  },
  {
    "id": 11,
    "title": "Fusão nuclear mais próxima de se tornar viável",
    "summary": "Pesquisadores atingem novo marco de eficiência energética.",
    "date": "2025-05-26"
  }
]
